[
  {
    "id": 1,
    "name": "Home Energy Audit",
    "description": "Identify energy efficiency improvements for your home.",
    "price": "$150",
    "image": "https://example.com/energy_audit.jpg"
  },
  {
    "id": 2,
    "name": "Pest Control",
    "description": "Effective removal and prevention of pests.",
    "price": "$120",
    "image": "https://example.com/pest_control.jpg"
  },
  {
    "id": 3,
    "name": "Gutter Cleaning",
    "description": "Clean and maintain your home's gutters and downspouts.",
    "price": "$100",
    "image": "https://example.com/gutter_cleaning.jpg"
  },
  {
    "id": 4,
    "name": "Chimney Sweep",
    "description": "Professional cleaning and inspection of chimneys.",
    "price": "$180",
    "image": "https://example.com/chimney_sweep.jpg"
  },
  {
    "id": 5,
    "name": "Home Security Installation",
    "description": "Install a modern security system to protect your home.",
    "price": "$250",
    "image": "https://example.com/home_security.jpg"
  }
  ]
  